allows/__init__.py
allows/exception.py
allows/factory.py
allows/grammar.py
allows/side_effect.py
allows-0.1.0.dist-info/AUTHORS.rst
allows-0.1.0.dist-info/LICENSE
allows-0.1.0.dist-info/METADATA
allows-0.1.0.dist-info/WHEEL
allows-0.1.0.dist-info/top_level.txt
allows-0.1.0.dist-info/RECORD
